picasso/__init__.py
picasso/__main__.py
picasso/aim.py
picasso/avgroi.py
picasso/clusterer.py
picasso/config_template.yaml
picasso/design.py
picasso/design_sequences.py
picasso/g5m.py
picasso/gausslq.py
picasso/gaussmle.py
picasso/imageprocess.py
picasso/io.py
picasso/lib.py
picasso/localize.py
picasso/masking.py
picasso/nanotron.py
picasso/postprocess.py
picasso/render.py
picasso/simulate.py
picasso/spinna.py
picasso/version.py
picasso/zfit.py
picasso/ext/__init__.py
picasso/ext/bitplane.py
picasso/gui/__init__.py
picasso/gui/average.py
picasso/gui/average3.py
picasso/gui/design.py
picasso/gui/filter.py
picasso/gui/localize.py
picasso/gui/nanotron.py
picasso/gui/render.py
picasso/gui/rotation.py
picasso/gui/simulate.py
picasso/gui/spinna.py
picasso/gui/toraw.py
picasso/gui/icons/average.ico
picasso/gui/icons/design.ico
picasso/gui/icons/filter.ico
picasso/gui/icons/localize.ico
picasso/gui/icons/nanotron.ico
picasso/gui/icons/picasso_server.png
picasso/gui/icons/render.ico
picasso/gui/icons/server.ico
picasso/gui/icons/simulate.ico
picasso/gui/icons/spinna.ico
picasso/gui/icons/toraw.ico
picasso/gui/notification_sounds/Bell.wav
picasso/gui/notification_sounds/Doorbell.wav
picasso/gui/notification_sounds/Magic.wav
picasso/gui/notification_sounds/Melodical_flute.wav
picasso/gui/notification_sounds/Ping.wav
picasso/gui/notification_sounds/Sci-fi.wav
picasso/gui/plugins/__init__.py
picasso/server/__init__.py
picasso/server/app.py
picasso/server/compare.py
picasso/server/helper.py
picasso/server/history.py
picasso/server/preview.py
picasso/server/status.py
picasso/server/watcher.py
picassosr-0.9.5.dist-info/licenses/LICENSE.txt
picassosr-0.9.5.dist-info/METADATA
picassosr-0.9.5.dist-info/WHEEL
picassosr-0.9.5.dist-info/entry_points.txt
picassosr-0.9.5.dist-info/top_level.txt
picassosr-0.9.5.dist-info/RECORD
