Metadata-Version: 2.4
Name: picassosr
Version: 0.9.5
Summary: Collection of tools for painting super-resolution images
Author-email: Joerg Schnitzbauer <joschnitzbauer@gmail.com>, "Maximilian T. Strauss" <straussmaximilian@gmail.com>, Rafal Kowalewski <rafalkowalewski998@gmail.com>
Project-URL: Homepage, https://github.com/jungmannlab/picasso
Project-URL: Documentation, https://picassosr.readthedocs.io/en/latest/index.html
Project-URL: Changelog, https://github.com/jungmannlab/picasso/blob/master/changelog.rst
Project-URL: Publications, https://doi.org/10.1038/nprot.2017.024
Keywords: super-resolution,DNA-PAINT,microscopy
Classifier: Development Status :: 4 - Beta
Classifier: Intended Audience :: Science/Research
Classifier: Programming Language :: Python
Classifier: Programming Language :: Python :: 3.10
Classifier: License :: OSI Approved :: MIT License
Classifier: Operating System :: OS Independent
Requires-Python: <3.11,>=3.10
License-File: LICENSE.txt
Requires-Dist: PyQt5
Requires-Dist: numpy==2.2.6
Requires-Dist: matplotlib==3.10.7
Requires-Dist: h5py==3.15.1
Requires-Dist: numba==0.62.1
Requires-Dist: scipy==1.15.3
Requires-Dist: pandas==2.3.3
Requires-Dist: tables==3.10.1
Requires-Dist: pyyaml==6.0.3
Requires-Dist: scikit-learn==1.7.2
Requires-Dist: tqdm==4.67.1
Requires-Dist: streamlit==1.50.0
Requires-Dist: nd2==0.10.4
Requires-Dist: sqlalchemy==2.0.44
Requires-Dist: plotly-express==0.4.1
Requires-Dist: watchdog==6.0.0
Requires-Dist: psutil==7.1.1
Requires-Dist: playsound3==3.2.8
Requires-Dist: imageio==2.37.0
Requires-Dist: imageio-ffmpeg==0.6.0
Requires-Dist: PyImarisWriter==0.7.0; sys_platform == "win32"
Provides-Extra: dev
Requires-Dist: build; extra == "dev"
Requires-Dist: black; extra == "dev"
Requires-Dist: pre-commit; extra == "dev"
Requires-Dist: twine; extra == "dev"
Requires-Dist: bumpversion; extra == "dev"
Dynamic: license-file
